multiqq/__init__.py
multiqq/adapter_aws.py
multiqq/adapter_beanstalkd.py
multiqq/adapter_mqtt.py
multiqq/adapter_redis.py
multiqq/adapters.py
multiqq-0.0.1.dist-info/LICENSE
multiqq-0.0.1.dist-info/METADATA
multiqq-0.0.1.dist-info/WHEEL
multiqq-0.0.1.dist-info/top_level.txt
multiqq-0.0.1.dist-info/RECORD
